inputErrorCheck/__init__.py
inputErrorCheck/checks.py
inputErrorChecking-0.5.11.dist-info/LICENSE
inputErrorChecking-0.5.11.dist-info/METADATA
inputErrorChecking-0.5.11.dist-info/WHEEL
inputErrorChecking-0.5.11.dist-info/top_level.txt
inputErrorChecking-0.5.11.dist-info/RECORD
