Metadata-Version: 2.1
Name: inputErrorChecking
Version: 0.5.11
Summary: A package to make user error catching and handling easier
Home-page: https://github.com/pypa/sampleproject
Author: TacitRonin20
Author-email: GLC0402@outlook.com
License: UNKNOWN
Project-URL: Bug Tracker, https://github.com/pypa/sampleproject/issues
Platform: UNKNOWN
Classifier: Programming Language :: Python :: 3
Classifier: License :: OSI Approved :: MIT License
Classifier: Operating System :: OS Independent
Requires-Python: >=3.6
License-File: LICENSE
